{
  "annotations": {
    "list": [
      {
        "builtIn": 1,
        "datasource": {
          "type": "grafana",
          "uid": "-- Grafana --"
        },
        "enable": true,
        "hide": true,
        "iconColor": "rgba(0, 211, 255, 1)",
        "name": "Annotations & Alerts",
        "target": {
          "limit": 100,
          "matchAny": false,
          "tags": [],
          "type": "dashboard"
        },
        "type": "dashboard"
      }
    ]
  },
  "editable": true,
  "graphTooltip": 0,
  "id": null,
  "links": [
    {
      "icon": "external link",
      "tags": [],
      "type": "dashboards"
    }
  ],
  "panels": [
    {
      "cacheTimeout": null,
      "colorBackground": true,
      "colorPrefix": false,
      "colorValue": false,
      "colors": [
        "#d44a3a",
        "rgba(237, 129, 40, 0.89)",
        "#299c46"
      ],
      "format": "none",
      "gauge": {
        "maxValue": 100,
        "minValue": 0,
        "show": false,
        "thresholdLabels": false,
        "thresholdMarkers": true
      },
      "gridPos": {
        "h": 5,
        "w": 6,
        "x": 0,
        "y": 0
      },
      "id": 2,
      "interval": null,
      "links": [],
      "mappingType": 1,
      "mappingTypes": [
        {
          "name": "value to text",
          "value": 1
        },
        {
          "name": "range to text",
          "value": 2
        }
      ],
      "maxDataPoints": 100,
      "nullPointMode": "connected",
      "nullText": null,
      "options": {},
      "pluginVersion": "11.5.1",
      "postfix": "",
      "postfixFontSize": "50%",
      "prefix": "",
      "prefixFontSize": "50%",
      "rangeMaps": [
        {
          "from": "null",
          "text": "N/A",
          "to": "null"
        }
      ],
      "sparkline": {
        "fillColor": "rgba(31, 118, 189, 0.18)",
        "full": false,
        "lineColor": "rgb(31, 120, 193)",
        "show": false
      },
      "tableColumn": "",
      "targets": [
        {
          "datasource": {
            "type": "prometheus",
            "uid": "prometheus"
          },
          "expr": "beanstalkd_up{job=~\"$job\",instance=~\"$instance\"}",
          "format": "time_series",
          "intervalFactor": 1,
          "legendFormat": "",
          "refId": "A"
        }
      ],
      "thresholds": "0,1",
      "timeFrom": null,
      "timeShift": null,
      "title": "Status",
      "type": "singlestat",
      "valueFontSize": "100%",
      "valueMaps": [
        {
          "op": "=",
          "text": "DOWN",
          "value": "0"
        },
        {
          "op": "=",
          "text": "UP",
          "value": "1"
        }
      ],
      "valueName": "current"
    },
    {
      "cacheTimeout": null,
      "colorBackground": false,
      "colorValue": false,
      "colors": [
        "#299c46",
        "rgba(237, 129, 40, 0.89)",
        "#d44a3a"
      ],
      "decimals": 1,
      "format": "s",
      "gauge": {
        "maxValue": 100,
        "minValue": 0,
        "show": false,
        "thresholdLabels": false,
        "thresholdMarkers": true
      },
      "gridPos": {
        "h": 5,
        "w": 6,
        "x": 6,
        "y": 0
      },
      "id": 10,
      "interval": null,
      "links": [],
      "mappingType": 1,
      "mappingTypes": [
        {
          "name": "value to text",
          "value": 1
        },
        {
          "name": "range to text",
          "value": 2
        }
      ],
      "maxDataPoints": 100,
      "nullPointMode": "connected",
      "nullText": null,
      "options": {},
      "postfix": "",
      "postfixFontSize": "50%",
      "prefix": "",
      "prefixFontSize": "50%",
      "rangeMaps": [
        {
          "from": "null",
          "text": "N/A",
          "to": "null"
        }
      ],
      "sparkline": {
        "fillColor": "rgba(31, 118, 189, 0.18)",
        "full": false,
        "lineColor": "rgb(31, 120, 193)",
        "show": false
      },
      "tableColumn": "",
      "targets": [
        {
          "datasource": {
            "type": "prometheus",
            "uid": "prometheus"
          },
          "expr": "beanstalkd_global_uptime{job=~\"$job\",instance=~\"$instance\"}",
          "format": "time_series",
          "intervalFactor": 1,
          "refId": "A"
        }
      ],
      "thresholds": "",
      "timeFrom": null,
      "timeShift": null,
      "title": "Uptime",
      "type": "singlestat",
      "valueFontSize": "70%",
      "valueMaps": [
        {
          "op": "=",
          "text": "N/A",
          "value": "null"
        }
      ],
      "valueName": "current"
    },
    {
      "cacheTimeout": null,
      "gridPos": {
        "h": 5,
        "w": 12,
        "x": 12,
        "y": 0
      },
      "id": 4,
      "links": [],
      "options": {
        "fieldOptions": {
          "calcs": [
            "last"
          ],
          "defaults": {
            "max": 50,
            "min": 0
          },
          "mappings": [],
          "override": {},
          "thresholds": [
            {
              "color": "green",
              "index": 0,
              "value": null
            },
            {
              "color": "red",
              "index": 1,
              "value": 30
            }
          ],
          "values": false
        },
        "orientation": "auto",
        "showThresholdLabels": false,
        "showThresholdMarkers": true
      },
      "pluginVersion": "11.5.1",
      "targets": [
        {
          "datasource": {
            "type": "prometheus",
            "uid": "prometheus"
          },
          "expr": "beanstalkd_global_current_connections{job=~\"$job\",instance=~\"$instance\"}",
          "format": "time_series",
          "intervalFactor": 1,
          "refId": "A"
        }
      ],
      "timeFrom": null,
      "timeShift": null,
      "title": "Connections",
      "type": "gauge"
    },
    {
      "gridPos": {
        "h": 8,
        "w": 12,
        "x": 0,
        "y": 5
      },
      "id": 8,
      "links": [],
      "options": {
        "displayMode": "lcd",
        "fieldOptions": {
          "calcs": [
            "last"
          ],
          "defaults": {
            "max": 20,
            "min": 0
          },
          "mappings": [],
          "override": {},
          "thresholds": [
            {
              "color": "green",
              "index": 0,
              "value": null
            },
            {
              "color": "red",
              "index": 1,
              "value": 10
            }
          ],
          "values": false
        },
        "orientation": "horizontal"
      },
      "targets": [
        {
          "datasource": {
            "type": "prometheus",
            "uid": "prometheus"
          },
          "expr": "beanstalkd_tube_current_jobs_ready{job=~\"$job\",instance=~\"$instance\"}",
          "format": "time_series",
          "instant": false,
          "intervalFactor": 1,
          "legendFormat": "{{instance}} - {{tube}}",
          "refId": "A"
        }
      ],
      "timeFrom": null,
      "timeShift": null,
      "title": "Queue length",
      "type": "bargauge"
    },
    {
      "aliasColors": {},
      "bars": false,
      "dashLength": 10,
      "dashes": false,
      "fill": 1,
      "gridPos": {
        "h": 8,
        "w": 12,
        "x": 12,
        "y": 5
      },
      "id": 7,
      "legend": {
        "avg": false,
        "current": false,
        "max": false,
        "min": false,
        "show": true,
        "total": false,
        "values": false
      },
      "lines": true,
      "linewidth": 1,
      "links": [],
      "nullPointMode": "null",
      "options": {},
      "percentage": false,
      "pointradius": 2,
      "points": false,
      "renderer": "flot",
      "seriesOverrides": [],
      "spaceLength": 10,
      "stack": false,
      "steppedLine": false,
      "targets": [
        {
          "datasource": {
            "type": "prometheus",
            "uid": "prometheus"
          },
          "expr": "beanstalkd_tube_current_jobs_ready{job=~\"$job\",instance=~\"$instance\"}",
          "format": "time_series",
          "instant": false,
          "intervalFactor": 1,
          "legendFormat": "{{instance}} - {{tube}}",
          "refId": "A"
        }
      ],
      "thresholds": [],
      "timeFrom": null,
      "timeRegions": [],
      "timeShift": null,
      "title": "Queue length",
      "tooltip": {
        "shared": true,
        "sort": 0,
        "value_type": "individual"
      },
      "type": "graph",
      "xaxis": {
        "buckets": null,
        "mode": "time",
        "name": null,
        "show": true,
        "values": []
      },
      "yaxes": [
        {
          "format": "short",
          "label": null,
          "logBase": 1,
          "max": null,
          "min": null,
          "show": true
        },
        {
          "format": "short",
          "label": null,
          "logBase": 1,
          "max": null,
          "min": null,
          "show": false
        }
      ],
      "yaxis": {
        "align": false,
        "alignLevel": null
      }
    },
    {
      "aliasColors": {},
      "bars": false,
      "dashLength": 10,
      "dashes": false,
      "fill": 1,
      "gridPos": {
        "h": 8,
        "w": 24,
        "x": 0,
        "y": 13
      },
      "id": 6,
      "legend": {
        "avg": false,
        "current": false,
        "max": false,
        "min": false,
        "show": true,
        "total": false,
        "values": false
      },
      "lines": true,
      "linewidth": 1,
      "links": [],
      "nullPointMode": "null",
      "options": {},
      "percentage": false,
      "pointradius": 2,
      "points": false,
      "renderer": "flot",
      "seriesOverrides": [],
      "spaceLength": 10,
      "stack": false,
      "steppedLine": false,
      "targets": [
        {
          "datasource": {
            "type": "prometheus",
            "uid": "prometheus"
          },
          "expr": "rate(beanstalkd_tube_total_jobs{job=~\"$job\",instance=~\"$instance\"}[1m])",
          "format": "time_series",
          "instant": false,
          "intervalFactor": 1,
          "legendFormat": "{{instance}} - {{tube}}",
          "refId": "A"
        }
      ],
      "thresholds": [],
      "timeFrom": null,
      "timeRegions": [],
      "timeShift": null,
      "title": "Jobs per second",
      "tooltip": {
        "shared": true,
        "sort": 0,
        "value_type": "individual"
      },
      "type": "graph",
      "xaxis": {
        "buckets": null,
        "mode": "time",
        "name": null,
        "show": true,
        "values": []
      },
      "yaxes": [
        {
          "format": "short",
          "label": null,
          "logBase": 1,
          "max": null,
          "min": null,
          "show": true
        },
        {
          "format": "short",
          "label": null,
          "logBase": 1,
          "max": null,
          "min": null,
          "show": false
        }
      ],
      "yaxis": {
        "align": false,
        "alignLevel": null
      }
    }
  ],
  "refresh": "",
  "schemaVersion": 40,
  "style": "dark",
  "tags": [],
  "templating": {
    "list": [
      {
        "datasource": {
          "type": "prometheus",
          "uid": "prometheus"
        },
        "definition": "label_values(up{job=~\"beanstalkd.*\"}, job)",
        "hide": 0,
        "includeAll": true,
        "label": "Job",
        "multi": true,
        "name": "job",
        "options": [],
        "query": {
          "query": "label_values(up{job=~\"beanstalkd.*\"}, job)",
          "refId": "StandardVariableQuery_Job_Beanstalkd"
        },
        "refresh": 1,
        "regex": "",
        "skipUrlSync": false,
        "sort": 1,
        "type": "query"
      },
      {
        "datasource": {
          "type": "prometheus",
          "uid": "prometheus"
        },
        "definition": "label_values(up{job=~\"$job\"}, instance)",
        "hide": 0,
        "includeAll": true,
        "label": "Instance",
        "multi": true,
        "name": "instance",
        "options": [],
        "query": {
          "query": "label_values(up{job=~\"$job\"}, instance)",
          "refId": "StandardVariableQuery_Instance_Beanstalkd"
        },
        "refresh": 1,
        "regex": "",
        "skipUrlSync": false,
        "sort": 1,
        "type": "query"
      }
    ]
  },
  "time": {
    "from": "now-6h",
    "to": "now"
  },
  "timepicker": {},
  "timezone": "",
  "title": "Queues",
  "uid": "dashboard-queues",
  "version": 1
}
